Workbook
Name Rendimento_Carteira: App!$D$12:$D$12

Sheet App
B10: Configurações
B11: Salário | D11: 2000
B12: Rendimento Carteira | D12: 0.006
B13: Sugestão de Investimento | D13: =D11*30% -> 600
B15: INVESTIMENTO MENSAL
B16: Quanto Investir por mês? | D16: 600
B17: Por quantos anos? | D17: 5
B18: Taxa de rendimento Mensal? | D18: 0.01079
B19: Patrimônio acumulado? | D19: =FV(D18,D17*12,D16*-1) -> 50266.148
B20: Dividendos Mensais? | D20: {=D19*Rendimento_Carteira} -> 301.59689
B22: Cenários | D22: Dividendo
A23: 2 | B23: Quanto em 2 anos | C23: =FV($D$18,$A23*12,$D$16*-1) -> 16336.576 | D23: =C23*$D$12 -> 98.019458
A24: 5 | B24: Quanto em 5 anos | C24: =FV($D$18,$A24*12,$D$16*-1) -> 50266.148 | D24: =C24*$D$12 -> 301.59689
A25: 10 | B25: Quanto em 10 anos | C25: =FV($D$18,$A25*12,$D$16*-1) -> 145970.53 | D25: =C25*$D$12 -> 875.82317
A26: 20 | B26: Quanto em 20 anos | C26: =FV($D$18,$A26*12,$D$16*-1) -> 675119.04 | D26: =C26*$D$12 -> 4050.7142
A27: 30 | B27: Quanto em 30 anos | C27: =FV($D$18,$A27*12,$D$16*-1) -> 2593301.8 | D27: =C27*$D$12 -> 15559.811
B30: Perfil | C30: Moderado
B31: Valor a ser investido por mês | C31: =D16 -> 600
B33: TIPO DE FII | C33: Percentual Sugerido | D33: Valores
B34: PAPEL | C34: =VLOOKUP($C$30&"-"&$B34,Base!A:D,4,FALSE) -> 0.32 | D34: =C34*$C$31 -> 192
B35: TIJOLO | C35: =VLOOKUP($C$30&"-"&$B35,Base!A:D,4,FALSE) -> 0.35 | D35: =C35*$C$31 -> 210
B36: HIBRIDOS | C36: =VLOOKUP($C$30&"-"&$B36,Base!A:D,4,FALSE) -> 0.08 | D36: =C36*$C$31 -> 48
B37: FOF'S | C37: =VLOOKUP($C$30&"-"&$B37,Base!A:D,4,FALSE) -> 0.05 | D37: =C37*$C$31 -> 30
B38: DESENVOLVIMENTOS | C38: =VLOOKUP($C$30&"-"&$B38,Base!A:D,4,FALSE) -> 0.1 | D38: =C38*$C$31 -> 60
B39: HOTELÁRIOS | C39: =VLOOKUP($C$30&"-"&$B39,Base!A:D,4,FALSE) -> 0.1 | D39: =C39*$C$31 -> 60
D40: =SUM(D34:D39) -> 600

Sheet Base
A1: Chave | B1: PERFIL | C1: TIPO DE FII | D1: %
A2: =B2&"-"&C2 -> Conservador-PAPEL | B2: Conservador | C2: PAPEL | D2: 0.3
A3: =B3&"-"&C3 -> Conservador-TIJOLO | B3: Conservador | C3: TIJOLO | D3: 0.5
A4: =B4&"-"&C4 -> Conservador-HIBRIDOS | B4: Conservador | C4: HIBRIDOS | D4: 0.1
A5: =B5&"-"&C5 -> Conservador-FOF'S | B5: Conservador | C5: FOF'S | D5: 0.1
A6: =B6&"-"&C6 -> Conservador-DESENVOLVIMENTOS | B6: Conservador | C6: DESENVOLVIMENTOS | D6: 0
A7: =B7&"-"&C7 -> Conservador-HOTELÁRIOS | B7: Conservador | C7: HOTELÁRIOS | D7: 0
A8: =B8&"-"&C8 -> Moderado-PAPEL | B8: Moderado | C8: PAPEL | D8: 0.32
A9: =B9&"-"&C9 -> Moderado-TIJOLO | B9: Moderado | C9: TIJOLO | D9: 0.35
A10: =B10&"-"&C10 -> Moderado-HIBRIDOS | B10: Moderado | C10: HIBRIDOS | D10: 0.08
A11: =B11&"-"&C11 -> Moderado-FOF'S | B11: Moderado | C11: FOF'S | D11: 0.05
A12: =B12&"-"&C12 -> Moderado-DESENVOLVIMENTOS | B12: Moderado | C12: DESENVOLVIMENTOS | D12: 0.1
A13: =B13&"-"&C13 -> Moderado-HOTELÁRIOS | B13: Moderado | C13: HOTELÁRIOS | D13: 0.1
... A19: =B19&"-"&C19 -> Agressivo-HOTELÁRIOS | B19: Agressivo | C19: HOTELÁRIOS | D19: 0.1
